SIAC/MCD43_GEE.py
SIAC/SIAC_L8.py
SIAC/SIAC_S2.py
SIAC/Two_NN.py
SIAC/VERSION
SIAC/__init__.py
SIAC/atmo_solver.py
SIAC/create_logger.py
SIAC/create_training_set.py
SIAC/downloaders.py
SIAC/get_MCD43.py
SIAC/kernels.py
SIAC/l8_angle.py
SIAC/l8_preprocessing.py
SIAC/lhd.py
SIAC/modis_tile_cal.py
SIAC/multi_process.py
SIAC/psf_optimize.py
SIAC/raster_boundary.py
SIAC/read_MCD43.py
SIAC/reproject.py
SIAC/s2_angle.py
SIAC/s2_angle_N0400.py
SIAC/s2_preprocessing.py
SIAC/smoothn.py
SIAC/the_aerosol.py
SIAC/the_correction.py
SIAC/data/.earthdata_auth
SIAC/data/pixel_s2_cloud_detector_lightGBM_v0.1.txt
SIAC/data/sen2cloud_detector.pkl
SIAC/emus/S2_TCWV.npz
SIAC/emus/isotropic_MSI_S2A_B01_xap.npz
SIAC/emus/isotropic_MSI_S2A_B01_xbp.npz
SIAC/emus/isotropic_MSI_S2A_B01_xcp.npz
SIAC/emus/isotropic_MSI_S2A_B02_xap.npz
SIAC/emus/isotropic_MSI_S2A_B02_xbp.npz
SIAC/emus/isotropic_MSI_S2A_B02_xcp.npz
SIAC/emus/isotropic_MSI_S2A_B03_xap.npz
SIAC/emus/isotropic_MSI_S2A_B03_xbp.npz
SIAC/emus/isotropic_MSI_S2A_B03_xcp.npz
SIAC/emus/isotropic_MSI_S2A_B04_xap.npz
SIAC/emus/isotropic_MSI_S2A_B04_xbp.npz
SIAC/emus/isotropic_MSI_S2A_B04_xcp.npz
SIAC/emus/isotropic_MSI_S2A_B05_xap.npz
SIAC/emus/isotropic_MSI_S2A_B05_xbp.npz
SIAC/emus/isotropic_MSI_S2A_B05_xcp.npz
SIAC/emus/isotropic_MSI_S2A_B06_xap.npz
SIAC/emus/isotropic_MSI_S2A_B06_xbp.npz
SIAC/emus/isotropic_MSI_S2A_B06_xcp.npz
SIAC/emus/isotropic_MSI_S2A_B07_xap.npz
SIAC/emus/isotropic_MSI_S2A_B07_xbp.npz
SIAC/emus/isotropic_MSI_S2A_B07_xcp.npz
SIAC/emus/isotropic_MSI_S2A_B08_xap.npz
SIAC/emus/isotropic_MSI_S2A_B08_xbp.npz
SIAC/emus/isotropic_MSI_S2A_B08_xcp.npz
SIAC/emus/isotropic_MSI_S2A_B09_xap.npz
SIAC/emus/isotropic_MSI_S2A_B09_xbp.npz
SIAC/emus/isotropic_MSI_S2A_B09_xcp.npz
SIAC/emus/isotropic_MSI_S2A_B10_xap.npz
SIAC/emus/isotropic_MSI_S2A_B10_xbp.npz
SIAC/emus/isotropic_MSI_S2A_B10_xcp.npz
SIAC/emus/isotropic_MSI_S2A_B11_xap.npz
SIAC/emus/isotropic_MSI_S2A_B11_xbp.npz
SIAC/emus/isotropic_MSI_S2A_B11_xcp.npz
SIAC-2.3.6.dist-info/AUTHORS.rst
SIAC-2.3.6.dist-info/LICENSE.md
SIAC-2.3.6.dist-info/METADATA
SIAC-2.3.6.dist-info/WHEEL
SIAC-2.3.6.dist-info/top_level.txt
SIAC-2.3.6.dist-info/RECORD
