Metadata-Version: 2.1
Name: SIAC
Version: 2.3.6
Summary: A sensor invariant Atmospheric Correction (SIAC)
Home-page: https://github.com/MarcYin/SIAC
Author: Feng Yin
Author-email: ucfafyi@ucl.ac.uk
License: GNU Affero General Public License v3.0
Classifier: Development Status :: 4 - Beta
Classifier: Programming Language :: Python :: 3.6
Classifier: Programming Language :: Python :: 3.7
License-File: LICENSE.md
License-File: AUTHORS.rst
Requires-Dist: gdal (>=2.1)
Requires-Dist: scipy (>=1.0)
Requires-Dist: psutil
Requires-Dist: six
Requires-Dist: numba
Requires-Dist: retry
Requires-Dist: earthengine-api
Requires-Dist: lightgbm (>=2.1.0)
Requires-Dist: requests
Requires-Dist: scikit-image
Requires-Dist: pyproj
